PrismSSL/__init__.py
PrismSSL/audio/Trainer.py
PrismSSL/audio/__init__.py
PrismSSL/audio/models/__init__.py
PrismSSL/audio/models/cola.py
PrismSSL/audio/models/eat.py
PrismSSL/audio/models/hubert.py
PrismSSL/audio/models/simclr.py
PrismSSL/audio/models/wav2vec2.py
PrismSSL/audio/models/modules/__init__.py
PrismSSL/audio/models/modules/backbones.py
PrismSSL/audio/models/modules/cola_backbone.py
PrismSSL/audio/models/modules/decoders.py
PrismSSL/audio/models/modules/eat_backbone.py
PrismSSL/audio/models/modules/feature_extractors.py
PrismSSL/audio/models/modules/heads.py
PrismSSL/audio/models/modules/hubert_backbone.py
PrismSSL/audio/models/modules/quantizer.py
PrismSSL/audio/models/modules/simclr_backbone.py
PrismSSL/audio/models/modules/wav2vec2_backbone.py
PrismSSL/audio/models/modules/losses/NTXent_loss.py
PrismSSL/audio/models/modules/losses/__init__.py
PrismSSL/audio/models/modules/losses/hubert_loss.py
PrismSSL/audio/models/modules/losses/infoNCE_loss.py
PrismSSL/audio/models/modules/losses/ufo_loss.py
PrismSSL/audio/models/modules/losses/wav2vec2_loss.py
PrismSSL/audio/models/modules/tools/__init__.py
PrismSSL/audio/models/modules/tools/pseudo_label_generator.py
PrismSSL/audio/models/modules/transformations/__init__.py
PrismSSL/audio/models/modules/transformations/cola_transform.py
PrismSSL/audio/models/modules/transformations/eat_transform.py
PrismSSL/audio/models/modules/transformations/simclr_transform.py
PrismSSL/audio/models/utils/__init__.py
PrismSSL/audio/models/utils/base_masking.py
PrismSSL/audio/models/utils/datasets.py
PrismSSL/audio/models/utils/evaluate.py
PrismSSL/audio/models/utils/registry.py
PrismSSL/graph/Trainer.py
PrismSSL/graph/__init__.py
PrismSSL/graph/models/__init__.py
PrismSSL/graph/models/graphcl.py
PrismSSL/graph/models/modules/__init__.py
PrismSSL/graph/models/modules/backbones.py
PrismSSL/graph/models/modules/heads.py
PrismSSL/graph/models/modules/losses/__init__.py
PrismSSL/graph/models/modules/losses/graphcl_loss.py
prism_ssl-0.2.1.dist-info/licenses/LICENSE
prism_ssl-0.2.1.dist-info/METADATA
prism_ssl-0.2.1.dist-info/WHEEL
prism_ssl-0.2.1.dist-info/top_level.txt
prism_ssl-0.2.1.dist-info/RECORD
