Metadata-Version: 2.4
Name: prism-ssl
Version: 0.2.1
Summary: A Self-Supervised Learning Library
Author: Melika Shirian
Author-email: Kianoosh Vadaei <kia.vadaei@gmail.com>
License: MIT License
Project-URL: Homepage, https://github.com/PrismaticLab/PrismSSL
Classifier: Development Status :: 3 - Alpha
Classifier: Intended Audience :: Science/Research
Classifier: Intended Audience :: Education
Classifier: License :: OSI Approved :: MIT License
Classifier: Programming Language :: Python :: 3
Classifier: Programming Language :: Python :: 3.10
Classifier: Programming Language :: Python :: 3.11
Classifier: Topic :: Scientific/Engineering :: Artificial Intelligence
Classifier: Topic :: Software Development :: Libraries :: Python Modules
Requires-Python: >=3.10
License-File: LICENSE
Requires-Dist: axial_positional_embedding
Requires-Dist: colorlog
Requires-Dist: editdistance
Requires-Dist: einops
Requires-Dist: huggingface_hub
Requires-Dist: jiwer
Requires-Dist: joblib
Requires-Dist: numpy
Requires-Dist: opencv_python
Requires-Dist: optuna
Requires-Dist: pandas
Requires-Dist: peft
Requires-Dist: Pillow
Requires-Dist: plotly
Requires-Dist: scikit_learn
Requires-Dist: setuptools
Requires-Dist: torch
Requires-Dist: torch_geometric
Requires-Dist: torchaudio
Requires-Dist: torcheval
Requires-Dist: torchmetrics
Requires-Dist: torchvision
Requires-Dist: tqdm
Requires-Dist: transformers
Requires-Dist: wandb
Requires-Dist: flask
Dynamic: license-file
Dynamic: requires-python
